[
    {
        "poster_image": "https://lumiere-a.akamaihd.net/v1/images/databank_ddttank_01_169_8b178f02.jpeg?region=195%2C0%2C1171%2C878"
    },
    {
        "poster_image": "https://lumiere-a.akamaihd.net/v1/images/delta-7-starfighter_fe9a59bc.jpeg?region=0%2C141%2C1560%2C1173"
    },
    {
        "poster_image": "https://lumiere-a.akamaihd.net/v1/images/skiff_9d81647a.jpeg?region=78%2C0%2C1404%2C1053"
    },
    {
        "poster_image": "https://lumiere-a.akamaihd.net/v1/images/droid_gunship_20546779.jpeg?region=210%2C0%2C1079%2C807"
    },
    {
        "poster_image": "https://lumiere-a.akamaihd.net/v1/images/enfys-nests-swoop-main_1024ae3a.jpeg?region=228%2C0%2C1159%2C867"
    },
    {
        "poster_image": "https://lumiere-a.akamaihd.net/v1/images/databank_executor_01_169_8157df82.jpeg?region=176%2C0%2C1170%2C878"
    },
    {
        "poster_image": "https://lumiere-a.akamaihd.net/v1/images/skiff_9d81647a.jpeg?region=78%2C0%2C1404%2C1053"
    },
    {
        "poster_image": "https://lumiere-a.akamaihd.net/v1/images/enfys-nests-swoop-main_1024ae3a.jpeg?region=228%2C0%2C1159%2C867"
    },
    {
        "poster_image": "https://lumiere-a.akamaihd.net/v1/images/gauntlet-fighter_b0ddbdb6.jpeg?region=244%2C0%2C1170%2C878"
    },
    {
        "poster_image": "https://lumiere-a.akamaihd.net/v1/images/finalizer_9c490246.jpeg?region=195%2C0%2C1171%2C878"
    },
    {
        "poster_image": "https://lumiere-a.akamaihd.net/v1/images/resistance-db-fireball-main-image_be52aeea.jpeg?region=122%2C0%2C1171%2C878"
    }
]
